python_elasticsearch_logging/__init__.py
python_elasticsearch_logging/_handlers.py
python_elasticsearch_logging/_queue_handler.py
python_elasticsearch_logging/_sending_handler.py
python_elasticsearch_logging-2.0.8.dist-info/LICENSE
python_elasticsearch_logging-2.0.8.dist-info/METADATA
python_elasticsearch_logging-2.0.8.dist-info/WHEEL
python_elasticsearch_logging-2.0.8.dist-info/RECORD
