Metadata-Version: 2.1
Name: python_elasticsearch_logging
Version: 2.0.8
Summary: Minimalistic Elasticsearch logging handler
Home-page: https://github.com/ashokpant/python-elasticsearch-logging
Keywords: elasticsearch,logging
Author: Bohdan Sydorov
Requires-Python: >=3.9,<4
Classifier: Programming Language :: Python :: 3
Classifier: Programming Language :: Python :: 3.9
Classifier: Programming Language :: Python :: 3.10
Classifier: Programming Language :: Python :: 3.11
Classifier: Programming Language :: Python :: 3.12
Classifier: Programming Language :: Python :: 3.13
Requires-Dist: elasticsearch (>=8.17.0,<9)
Requires-Dist: pytz (>=2024.2)
Requires-Dist: urllib3 (>=2.2.2,<2.3.0)
Project-URL: Repository, https://github.com/ashokpant/python-elasticsearch-logging
